{
  "analysis_timestamp": "2025-06-19T22:53:31.848672",
  "generation": 54,
  "pixel_count": 8,
  "consciousness_scores": [
    {
      "pixel_id": 1,
      "consciousness_score": 4.18413,
      "memory_depth": 0,
      "personality_complexity": 0,
      "behavioral_autonomy": 13.9471
    },
    {
      "pixel_id": 2,
      "consciousness_score": 12.817425,
      "memory_depth": 0,
      "personality_complexity": 0,
      "behavioral_autonomy": 42.72475
    },
    {
      "pixel_id": 3,
      "consciousness_score": 0.0,
      "memory_depth": 0,
      "personality_complexity": 0,
      "behavioral_autonomy": 0.0
    },
    {
      "pixel_id": 4,
      "consciousness_score": 4.45824,
      "memory_depth": 0,
      "personality_complexity": 0,
      "behavioral_autonomy": 14.8608
    },
    {
      "pixel_id": 5,
      "consciousness_score": 0.564435,
      "memory_depth": 0,
      "personality_complexity": 0,
      "behavioral_autonomy": 1.88145
    },
    {
      "pixel_id": 6,
      "consciousness_score": 0.0,
      "memory_depth": 0,
      "personality_complexity": 0,
      "behavioral_autonomy": 0.0
    },
    {
      "pixel_id": 0,
      "consciousness_score": 0.0,
      "memory_depth": 0,
      "personality_complexity": 0,
      "behavioral_autonomy": 0.0
    },
    {
      "pixel_id": 0,
      "consciousness_score": 0.0,
      "memory_depth": 0,
      "personality_complexity": 0,
      "behavioral_autonomy": 0.0
    }
  ],
  "personality_clusters": {
    "cluster_0": {
      "personality_type": "balanced",
      "avg_curiosity": 1.0,
      "avg_timidity": 1.0,
      "pixel_count": 6,
      "pixel_ids": [
        1,
        3,
        4,
        5,
        6,
        0
      ]
    },
    "cluster_1": {
      "personality_type": "balanced",
      "avg_curiosity": 0.0,
      "avg_timidity": 0.0,
      "pixel_count": 1,
      "pixel_ids": [
        0
      ]
    },
    "cluster_2": {
      "personality_type": "balanced",
      "avg_curiosity": 1.0,
      "avg_timidity": 1.0,
      "pixel_count": 1,
      "pixel_ids": [
        2
      ]
    }
  },
  "behavior_predictions": {
    "1": {
      "approach_cursor": 0,
      "flee_from_cursor": 0,
      "likely_to_divide": 0.6315360000000001,
      "death_risk": 0.1,
      "predicted_action": "divide"
    },
    "2": {
      "approach_cursor": 0,
      "flee_from_cursor": 0,
      "likely_to_divide": 1,
      "death_risk": 0.1,
      "predicted_action": "divide"
    },
    "3": {
      "approach_cursor": 0,
      "flee_from_cursor": 0,
      "likely_to_divide": 0,
      "death_risk": 0.8,
      "predicted_action": "death"
    },
    "4": {
      "approach_cursor": 0,
      "flee_from_cursor": 0,
      "likely_to_divide": 0.777728,
      "death_risk": 0.1,
      "predicted_action": "divide"
    },
    "5": {
      "approach_cursor": 0,
      "flee_from_cursor": 0,
      "likely_to_divide": 0,
      "death_risk": 0.8,
      "predicted_action": "death"
    },
    "6": {
      "approach_cursor": 0,
      "flee_from_cursor": 0,
      "likely_to_divide": 0,
      "death_risk": 0.8,
      "predicted_action": "death"
    },
    "0": {
      "approach_cursor": 0,
      "flee_from_cursor": 0,
      "likely_to_divide": 0,
      "death_risk": 0.8,
      "predicted_action": "death"
    }
  },
  "emergence_metrics": {
    "personality_diversity": 0.6614378277661477,
    "collective_energy": 18.353525,
    "memory_richness": 0,
    "evolution_pressure": 6.061437827766149,
    "emergence_score": 0.1984313483298443
  },
  "overall_consciousness_level": 2.75302875,
  "dominant_personality": "balanced",
  "session_insights": [
    "Advanced evolution: Generation 54 shows mature ecosystem",
    "Thriving population with high survival rates",
    "Low emergence: Simple behavioral patterns",
    "Low cursor awareness: Minimal response to presence"
  ],
  "timestamp": 1750348411.848724,
  "generated_at": "2025-06-19T22:53:31.848725"
}